baccmod/__init__.py
baccmod/base_acceptance_map_creator.py
baccmod/bkg_collection.py
baccmod/exception.py
baccmod/grid3d_acceptance_map_creator.py
baccmod/logging.py
baccmod/modeling.py
baccmod/radial_acceptance_map_creator.py
baccmod/toolbox.py
baccmod-0.4.0.dist-info/licenses/LICENCE.txt
baccmod-0.4.0.dist-info/METADATA
baccmod-0.4.0.dist-info/WHEEL
baccmod-0.4.0.dist-info/top_level.txt
baccmod-0.4.0.dist-info/RECORD
