Metadata-Version: 2.4
Name: BAccMod
Version: 0.4.0
Summary: Calculate 2D and 3d acceptance model for creating maps with gammapy (IACT analysis)
Home-page: https://github.com/mdebony/BAccMod
Author: Mathieu de Bony de Lavergne, Gabriel Emery, Marie-Sophie Carrasco
Author-email: debony@cppm.in2p3.fr
License: LGPL v3
License-File: LICENCE.txt
Requires-Dist: gammapy<2.1,>=1.1
Requires-Dist: numpy<2.4
Requires-Dist: scipy<1.17
Requires-Dist: iminuit<3.0,>=2.0
Requires-Dist: astropy<8.0,>=4.0
Requires-Dist: regions<0.11,>=0.7
Dynamic: author
Dynamic: author-email
Dynamic: description
Dynamic: description-content-type
Dynamic: home-page
Dynamic: license
Dynamic: license-file
Dynamic: requires-dist
Dynamic: summary
